vutils/validator/__init__.py
vutils/validator/__init__.pyi
vutils/validator/basic.py
vutils/validator/errors.py
vutils/validator/py.typed
vutils/validator/schema.py
vutils/validator/value.py
vutils/validator/version.py
vutils_validator-0.2.0.dist-info/LICENSE
vutils_validator-0.2.0.dist-info/METADATA
vutils_validator-0.2.0.dist-info/WHEEL
vutils_validator-0.2.0.dist-info/top_level.txt
vutils_validator-0.2.0.dist-info/RECORD
