Metadata-Version: 2.1
Name: vutils-validator
Version: 0.2.0
Summary: Data validation utilities
Home-page: https://github.com/i386x/vutils-validator
Author: Jiří Kučera
Author-email: sanczes@gmail.com
License: MIT
Project-URL: Bug Reports, https://github.com/i386x/vutils-validator/issues
Project-URL: Source, https://github.com/i386x/vutils-validator
Keywords: data,schema,validation
Platform: any
Classifier: Development Status :: 1 - Planning
Classifier: Intended Audience :: Developers
Classifier: Intended Audience :: Information Technology
Classifier: License :: OSI Approved :: MIT License
Classifier: Operating System :: OS Independent
Classifier: Programming Language :: Python
Classifier: Programming Language :: Python :: 3
Classifier: Programming Language :: Python :: 3 :: Only
Classifier: Topic :: Software Development
Classifier: Topic :: Software Development :: Libraries :: Python Modules
Classifier: Topic :: Utilities
Requires-Python: <4,>=3.7
License-File: LICENSE
Requires-Dist: jsonschema
Provides-Extra: dev
Requires-Dist: tox ; extra == 'dev'
Provides-Extra: test
Requires-Dist: tox ; extra == 'test'
